[
    {
        "id": "f6f2187d.f17ca8",
        "type": "tab",
        "label": "FLUJO DE INTEGRADOR :)",
        "disabled": false,
        "info": ""
    },
    {
        "id": "96c825bc45002041",
        "type": "group",
        "z": "f6f2187d.f17ca8",
        "name": "Obtención de información del ambiente",
        "style": {
            "stroke": "#a4a4a4",
            "fill": "#ffC000",
            "label": true,
            "label-position": "n",
            "color": "#000000"
        },
        "nodes": [
            "f33b1970bae58ab6",
            "c722252e9249c5f9",
            "863e8239018e9dae",
            "3994be954795c847",
            "f11e71571034be14",
            "ab0b13e1bc4e7044",
            "ec0dc0eb5facfeb2",
            "9e29228f87aa3710",
            "a2d9682082327b7c",
            "99bfa1f6dacb461d",
            "9599be435b82c01b"
        ],
        "x": 14,
        "y": -1,
        "w": 1032,
        "h": 302
    },
    {
        "id": "651945f5b9f2fc9a",
        "type": "group",
        "z": "f6f2187d.f17ca8",
        "name": "Configuración de temperatura",
        "style": {
            "stroke": "#000000",
            "fill": "#ff7f7f",
            "label": true,
            "label-position": "n",
            "color": "#000000"
        },
        "nodes": [
            "404e24dfc47c02f9",
            "d7ea58614ed76a84",
            "6603efe9830e1ade",
            "b849b744cc6e3f1d",
            "22a2b24ce927b6b8"
        ],
        "x": 14,
        "y": 839,
        "w": 752,
        "h": 202
    },
    {
        "id": "a3163b138a0b2545",
        "type": "group",
        "z": "f6f2187d.f17ca8",
        "name": "Configuración de humedad",
        "style": {
            "stroke": "#000000",
            "fill": "#7fb7df",
            "label": true,
            "label-position": "n",
            "color": "#000000"
        },
        "nodes": [
            "bea79c4d30ca8777",
            "90e3b92898d0092d",
            "d1a26b86e207c2f5",
            "292fe07942469879"
        ],
        "x": 14,
        "y": 579,
        "w": 692,
        "h": 202
    },
    {
        "id": "4b1949201b6cb715",
        "type": "group",
        "z": "f6f2187d.f17ca8",
        "name": "Configuración de deep_sleep",
        "style": {
            "stroke": "#000000",
            "fill": "#9363b7",
            "label": true,
            "label-position": "n",
            "color": "#000000"
        },
        "nodes": [
            "0356df8078018ac3",
            "b89e2be1477e815e",
            "b55e9996505a42be",
            "1bc8d45287baadc4",
            "f468befd970ba541"
        ],
        "x": 14,
        "y": 339,
        "w": 792,
        "h": 202
    },
    {
        "id": "863e8239018e9dae",
        "type": "junction",
        "z": "f6f2187d.f17ca8",
        "g": "96c825bc45002041",
        "x": 420,
        "y": 120,
        "wires": [
            []
        ]
    },
    {
        "id": "f33b1970bae58ab6",
        "type": "mqtt in",
        "z": "f6f2187d.f17ca8",
        "g": "96c825bc45002041",
        "name": "",
        "topic": "sensores/ambiente",
        "qos": "2",
        "datatype": "auto-detect",
        "broker": "4c42f4f5f0c456f7",
        "nl": false,
        "rap": true,
        "rh": 0,
        "inputs": 0,
        "x": 130,
        "y": 120,
        "wires": [
            [
                "c722252e9249c5f9",
                "3994be954795c847"
            ]
        ]
    },
    {
        "id": "c722252e9249c5f9",
        "type": "debug",
        "z": "f6f2187d.f17ca8",
        "g": "96c825bc45002041",
        "name": "debug 1",
        "active": true,
        "tosidebar": true,
        "console": false,
        "tostatus": false,
        "complete": "payload",
        "targetType": "msg",
        "statusVal": "",
        "statusType": "auto",
        "x": 340,
        "y": 40,
        "wires": []
    },
    {
        "id": "3994be954795c847",
        "type": "function",
        "z": "f6f2187d.f17ca8",
        "g": "96c825bc45002041",
        "name": "formateador",
        "func": "const temperatura = msg.payload.temperatura;\nconst humedad = msg.payload.humedad;\nconst dispositivo = msg.payload.dispositivo;\n\n\nmsg.payload = `ambiente,dispositivo=${dispositivo} temperatura=${temperatura},humedad=${humedad}`;\nmsg.datos = {\n    dispositivo: dispositivo,\n    temperatura: temperatura,\n    humedad: humedad\n};\n\nreturn msg\n",
        "outputs": 1,
        "timeout": 0,
        "noerr": 0,
        "initialize": "",
        "finalize": "",
        "libs": [],
        "x": 370,
        "y": 200,
        "wires": [
            [
                "f11e71571034be14",
                "a2d9682082327b7c",
                "99bfa1f6dacb461d"
            ]
        ]
    },
    {
        "id": "f11e71571034be14",
        "type": "http request",
        "z": "f6f2187d.f17ca8",
        "g": "96c825bc45002041",
        "name": "influx-post",
        "method": "POST",
        "ret": "txt",
        "paytoqs": "body",
        "url": "influxdb-1:8086/write?db=iot",
        "tls": "",
        "persist": false,
        "proxy": "",
        "insecureHTTPParser": true,
        "authType": "",
        "senderr": false,
        "headers": [
            {
                "keyType": "Content-Type",
                "keyValue": "",
                "valueType": "text/plain",
                "valueValue": ""
            }
        ],
        "x": 590,
        "y": 260,
        "wires": [
            []
        ]
    },
    {
        "id": "404e24dfc47c02f9",
        "type": "telegram command",
        "z": "f6f2187d.f17ca8",
        "g": "651945f5b9f2fc9a",
        "name": "",
        "command": "/configurar_temperatura",
        "description": "Configuracion de temperatura",
        "registercommand": false,
        "language": "",
        "scope": "all_private_chats",
        "bot": "02d0723b5e9b15f8",
        "strict": false,
        "hasresponse": false,
        "useregex": false,
        "removeregexcommand": false,
        "outputs": 1,
        "x": 140,
        "y": 940,
        "wires": [
            [
                "b849b744cc6e3f1d",
                "6603efe9830e1ade"
            ]
        ]
    },
    {
        "id": "bea79c4d30ca8777",
        "type": "telegram command",
        "z": "f6f2187d.f17ca8",
        "g": "a3163b138a0b2545",
        "name": "",
        "command": "/configurar_humedad",
        "description": "",
        "registercommand": false,
        "language": "",
        "scope": "default",
        "bot": "02d0723b5e9b15f8",
        "strict": false,
        "hasresponse": false,
        "useregex": false,
        "removeregexcommand": false,
        "outputs": 1,
        "x": 140,
        "y": 680,
        "wires": [
            [
                "d1a26b86e207c2f5",
                "292fe07942469879"
            ]
        ]
    },
    {
        "id": "d7ea58614ed76a84",
        "type": "telegram sender",
        "z": "f6f2187d.f17ca8",
        "g": "651945f5b9f2fc9a",
        "name": "",
        "bot": "02d0723b5e9b15f8",
        "haserroroutput": false,
        "outputs": 1,
        "x": 650,
        "y": 880,
        "wires": [
            []
        ]
    },
    {
        "id": "6603efe9830e1ade",
        "type": "function",
        "z": "f6f2187d.f17ca8",
        "g": "651945f5b9f2fc9a",
        "name": "function 2",
        "func": "const content = msg.payload.content;\n\nif(content === \"\"){\n    return \"\";\n}\nelse {\n    const value = Number(content);\n\n    if (typeof value === 'number' && value >= 0 && value <= 100){\n        global.set(\"alertaTemperatura\", value);\n    }\n    else {\n        return \"\"\n    }\n}\n\n",
        "outputs": 1,
        "timeout": 0,
        "noerr": 0,
        "initialize": "",
        "finalize": "",
        "libs": [],
        "x": 360,
        "y": 1000,
        "wires": [
            []
        ]
    },
    {
        "id": "b849b744cc6e3f1d",
        "type": "function",
        "z": "f6f2187d.f17ca8",
        "g": "651945f5b9f2fc9a",
        "name": "function 4",
        "func": "const content = msg.payload.content;\n\nif(content === \"\"){\n    msg.payload.content = \"Por favor use el comando ingresando la temperatura deseada a configurar\\n \\\n    los valores validos son desde 0 hasta 100 C°\";\n    return msg;\n}\n\nconst value = Number(content);\n\nif (typeof value === 'number' && value >= 0 && value <= 100){\n    msg.payload.content = `valor de ${value} configurado para temperatura`;\n}\nelse {\n    msg.payload.content = \"ups\";\n}\n\nreturn msg;\n",
        "outputs": 1,
        "timeout": 0,
        "noerr": 0,
        "initialize": "",
        "finalize": "",
        "libs": [],
        "x": 360,
        "y": 880,
        "wires": [
            [
                "d7ea58614ed76a84",
                "22a2b24ce927b6b8"
            ]
        ]
    },
    {
        "id": "90e3b92898d0092d",
        "type": "telegram sender",
        "z": "f6f2187d.f17ca8",
        "g": "a3163b138a0b2545",
        "name": "",
        "bot": "02d0723b5e9b15f8",
        "haserroroutput": false,
        "outputs": 1,
        "x": 590,
        "y": 620,
        "wires": [
            []
        ]
    },
    {
        "id": "d1a26b86e207c2f5",
        "type": "function",
        "z": "f6f2187d.f17ca8",
        "g": "a3163b138a0b2545",
        "name": "function 1",
        "func": "const content = msg.payload.content;\n\nif(content === \"\"){\n    msg.payload.content = \"Por favor use el comando ingresando la temperatura deseada a configurar\\n \\\n    los valores validos son desde 0 hasta 100 %\";\n    return msg;\n}\n\nconst value = Number(content);\n\nif (typeof value === 'number' && value >= 0 && value <= 100){\n    msg.payload.content = `valor de ${value}% configurado para humedad`;\n}\nelse {\n    msg.payload.content = \"ups\";\n}\n\nreturn msg;\n",
        "outputs": 1,
        "timeout": 0,
        "noerr": 0,
        "initialize": "",
        "finalize": "",
        "libs": [],
        "x": 360,
        "y": 620,
        "wires": [
            [
                "90e3b92898d0092d"
            ]
        ]
    },
    {
        "id": "292fe07942469879",
        "type": "function",
        "z": "f6f2187d.f17ca8",
        "g": "a3163b138a0b2545",
        "name": "function 3",
        "func": "const content = msg.payload.content;\n\nglobal.set(\"usuario\", { nombre: \"Juan\", edad: 30 });\n\nif(content === \"\"){\n}\nelse {\n    const value = Number(content);\n\n    if (typeof value === 'number' && value >= 0 && value <= 100){\n        global.set(\"alertaHumedad\", value);\n    }\n}\n\n",
        "outputs": 1,
        "timeout": 0,
        "noerr": 0,
        "initialize": "",
        "finalize": "",
        "libs": [],
        "x": 360,
        "y": 740,
        "wires": [
            []
        ]
    },
    {
        "id": "0356df8078018ac3",
        "type": "telegram command",
        "z": "f6f2187d.f17ca8",
        "g": "4b1949201b6cb715",
        "name": "",
        "command": "/configurar_deep_sleep",
        "description": "",
        "registercommand": false,
        "language": "",
        "scope": "default",
        "bot": "02d0723b5e9b15f8",
        "strict": false,
        "hasresponse": false,
        "useregex": false,
        "removeregexcommand": false,
        "outputs": 1,
        "x": 140,
        "y": 440,
        "wires": [
            [
                "b55e9996505a42be",
                "1bc8d45287baadc4"
            ]
        ]
    },
    {
        "id": "b89e2be1477e815e",
        "type": "telegram sender",
        "z": "f6f2187d.f17ca8",
        "g": "4b1949201b6cb715",
        "name": "",
        "bot": "02d0723b5e9b15f8",
        "haserroroutput": false,
        "outputs": 1,
        "x": 590,
        "y": 380,
        "wires": [
            []
        ]
    },
    {
        "id": "b55e9996505a42be",
        "type": "function",
        "z": "f6f2187d.f17ca8",
        "g": "4b1949201b6cb715",
        "name": "function 5",
        "func": "const content = msg.payload.content;\n\nif(content === \"\"){\n    msg.payload.content = \"Por favor use el comando ingresando el tiempo deseado en minutos, los valores validos son enteros mayores a 0\";\n    return msg;\n}\n\nconst value = Number(content);\n\nif (typeof value === 'number' && value > 0){\n    msg.payload.content = `valor de ${value}' configurado como tiempo entre mediciones`;\n}\nelse {\n    msg.payload.content = \"ups\";\n}\n\nreturn msg;\n",
        "outputs": 1,
        "timeout": 0,
        "noerr": 0,
        "initialize": "",
        "finalize": "",
        "libs": [],
        "x": 360,
        "y": 380,
        "wires": [
            [
                "b89e2be1477e815e"
            ]
        ]
    },
    {
        "id": "1bc8d45287baadc4",
        "type": "function",
        "z": "f6f2187d.f17ca8",
        "g": "4b1949201b6cb715",
        "name": "function 6",
        "func": "const content = msg.payload.content;\n\nif(content === \"\"){\n    return \"\";\n}\nelse {\n    const value = Number(content);\n\n    if (typeof value === 'number' && value > 0 ){\n        msg.payload = {valor: value, limite:\"deep_sleep\"};\n        return msg;\n    }\n    else {\n        return \"\"\n    }\n}\n\n",
        "outputs": 1,
        "timeout": 0,
        "noerr": 0,
        "initialize": "",
        "finalize": "",
        "libs": [],
        "x": 360,
        "y": 500,
        "wires": [
            [
                "f468befd970ba541"
            ]
        ]
    },
    {
        "id": "f468befd970ba541",
        "type": "mqtt out",
        "z": "f6f2187d.f17ca8",
        "g": "4b1949201b6cb715",
        "name": "",
        "topic": "sensores/configuracion/deep_sleep",
        "qos": "1",
        "retain": "true",
        "respTopic": "",
        "contentType": "",
        "userProps": "",
        "correl": "",
        "expiry": "",
        "broker": "4c42f4f5f0c456f7",
        "x": 640,
        "y": 500,
        "wires": []
    },
    {
        "id": "dd5d28d8c9bbd9a5",
        "type": "mqtt in",
        "z": "f6f2187d.f17ca8",
        "name": "",
        "topic": "sensores/configuracion/deep_sleep",
        "qos": "1",
        "datatype": "auto-detect",
        "broker": "4c42f4f5f0c456f7",
        "nl": false,
        "rap": true,
        "rh": 0,
        "inputs": 0,
        "x": 1320,
        "y": 140,
        "wires": [
            [
                "ee2cf4a7d9125196"
            ]
        ]
    },
    {
        "id": "ee2cf4a7d9125196",
        "type": "debug",
        "z": "f6f2187d.f17ca8",
        "name": "debug 2",
        "active": true,
        "tosidebar": true,
        "console": false,
        "tostatus": false,
        "complete": "false",
        "statusVal": "",
        "statusType": "auto",
        "x": 1580,
        "y": 140,
        "wires": []
    },
    {
        "id": "ab0b13e1bc4e7044",
        "type": "function",
        "z": "f6f2187d.f17ca8",
        "g": "96c825bc45002041",
        "name": "function 7",
        "func": "/*\ng.payload must be an object that contains a complete set of telegram message properties, at a minimum these should contain:\n\n    content the message contents\n    type the type of message contents\n    chatId the chatId number or an array of chatIds\n*/\n\nconst valores = msg.datos;\nmsg = {}\n\nmsg.payload = {}\nmsg.payload.content = `La temperatura esta alta :( se detecto ${valores.temperatura} °C`\nmsg.payload.type = \"message\"\nmsg.payload.chatId = -5448474721\n\n\n\n    \nreturn msg;\n",
        "outputs": 1,
        "timeout": 0,
        "noerr": 0,
        "initialize": "",
        "finalize": "",
        "libs": [],
        "x": 720,
        "y": 80,
        "wires": [
            [
                "ec0dc0eb5facfeb2",
                "9e29228f87aa3710"
            ]
        ]
    },
    {
        "id": "22a2b24ce927b6b8",
        "type": "debug",
        "z": "f6f2187d.f17ca8",
        "g": "651945f5b9f2fc9a",
        "name": "debug 3",
        "active": true,
        "tosidebar": true,
        "console": false,
        "tostatus": false,
        "complete": "false",
        "statusVal": "",
        "statusType": "auto",
        "x": 530,
        "y": 960,
        "wires": []
    },
    {
        "id": "ec0dc0eb5facfeb2",
        "type": "debug",
        "z": "f6f2187d.f17ca8",
        "g": "96c825bc45002041",
        "name": "debug 4",
        "active": true,
        "tosidebar": true,
        "console": false,
        "tostatus": false,
        "complete": "true",
        "targetType": "full",
        "statusVal": "",
        "statusType": "auto",
        "x": 920,
        "y": 40,
        "wires": []
    },
    {
        "id": "9e29228f87aa3710",
        "type": "telegram sender",
        "z": "f6f2187d.f17ca8",
        "g": "96c825bc45002041",
        "name": "",
        "bot": "02d0723b5e9b15f8",
        "haserroroutput": false,
        "outputs": 1,
        "x": 930,
        "y": 120,
        "wires": [
            []
        ]
    },
    {
        "id": "a2d9682082327b7c",
        "type": "switch",
        "z": "f6f2187d.f17ca8",
        "g": "96c825bc45002041",
        "name": "",
        "property": "datos.temperatura",
        "propertyType": "msg",
        "rules": [
            {
                "t": "gte",
                "v": "alertaTemperatura",
                "vt": "global"
            }
        ],
        "checkall": "true",
        "repair": false,
        "outputs": 1,
        "x": 570,
        "y": 120,
        "wires": [
            [
                "ab0b13e1bc4e7044"
            ]
        ]
    },
    {
        "id": "99bfa1f6dacb461d",
        "type": "switch",
        "z": "f6f2187d.f17ca8",
        "g": "96c825bc45002041",
        "name": "",
        "property": "datos.humedad",
        "propertyType": "msg",
        "rules": [
            {
                "t": "gte",
                "v": "alertaHumedad",
                "vt": "global"
            }
        ],
        "checkall": "true",
        "repair": false,
        "outputs": 1,
        "x": 570,
        "y": 180,
        "wires": [
            [
                "9599be435b82c01b"
            ]
        ]
    },
    {
        "id": "9599be435b82c01b",
        "type": "function",
        "z": "f6f2187d.f17ca8",
        "g": "96c825bc45002041",
        "name": "function 8",
        "func": "/*\ng.payload must be an object that contains a complete set of telegram message properties, at a minimum these should contain:\n\n    content the message contents\n    type the type of message contents\n    chatId the chatId number or an array of chatIds\n*/\n\nconst valores = msg.datos;\nmsg = {}\n\nmsg.payload = {}\nmsg.payload.content = `La humedad esta alta :( se detecto ${valores.humedad} %`\nmsg.payload.type = \"message\"\nmsg.payload.chatId = -5448474721\n\n\nreturn msg;",
        "outputs": 1,
        "timeout": 0,
        "noerr": 0,
        "initialize": "",
        "finalize": "",
        "libs": [],
        "x": 720,
        "y": 180,
        "wires": [
            [
                "9e29228f87aa3710"
            ]
        ]
    },
    {
        "id": "089315b35678f760",
        "type": "telegram command",
        "z": "f6f2187d.f17ca8",
        "name": "",
        "command": "/suscribirse",
        "description": "",
        "registercommand": false,
        "language": "",
        "scope": "default",
        "bot": "02d0723b5e9b15f8",
        "strict": false,
        "hasresponse": false,
        "useregex": false,
        "removeregexcommand": false,
        "outputs": 1,
        "x": 950,
        "y": 420,
        "wires": [
            [
                "fb4c42443da7588f"
            ]
        ]
    },
    {
        "id": "fb4c42443da7588f",
        "type": "function",
        "z": "f6f2187d.f17ca8",
        "name": "function 9",
        "func": "if(\"chats\" in global.keys){\n    const id = msg.payload.chatId;\n    if(!global.get(\"chats\").includes(id))\n        global.get(\"chats\").push(id)\n    msg = {}\n    msg.chats = global.get(\"chats\")\n    return msg\n}\nelse{\n    const id = msg.payload.chatId\n    global.set(\"chats\", [id]);\n    msg = {}\n    msg.keys = global.keys()\n    msg.chats = global.get()\n    return msg\n}\n",
        "outputs": 1,
        "timeout": 0,
        "noerr": 1,
        "initialize": "",
        "finalize": "",
        "libs": [],
        "x": 1140,
        "y": 420,
        "wires": [
            [
                "f628f587973fe414"
            ]
        ]
    },
    {
        "id": "f628f587973fe414",
        "type": "debug",
        "z": "f6f2187d.f17ca8",
        "name": "debug 5",
        "active": true,
        "tosidebar": true,
        "console": true,
        "tostatus": false,
        "complete": "true",
        "targetType": "full",
        "statusVal": "",
        "statusType": "auto",
        "x": 1320,
        "y": 360,
        "wires": []
    },
    {
        "id": "4c42f4f5f0c456f7",
        "type": "mqtt-broker",
        "name": "",
        "broker": "mqtt",
        "port": 1883,
        "clientid": "",
        "autoConnect": true,
        "usetls": false,
        "protocolVersion": 4,
        "keepalive": 60,
        "cleansession": true,
        "autoUnsubscribe": true,
        "birthTopic": "",
        "birthQos": "0",
        "birthRetain": "false",
        "birthPayload": "",
        "birthMsg": {},
        "closeTopic": "",
        "closeQos": "0",
        "closeRetain": "false",
        "closePayload": "",
        "closeMsg": {},
        "willTopic": "",
        "willQos": "0",
        "willRetain": "false",
        "willPayload": "",
        "willMsg": {},
        "userProps": "",
        "sessionExpiry": ""
    },
    {
        "id": "02d0723b5e9b15f8",
        "type": "telegram bot",
        "botname": "Iot-test",
        "usernames": "",
        "chatids": "",
        "baseapiurl": "",
        "testenvironment": false,
        "updatemode": "polling",
        "pollinterval": 300,
        "usesocks": false,
        "sockshost": "",
        "socksprotocol": "socks5",
        "socksport": 6667,
        "socksusername": "anonymous",
        "sockspassword": "",
        "bothost": "",
        "botpath": "",
        "localbothost": "0.0.0.0",
        "localbotport": 8443,
        "publicbotport": 8443,
        "privatekey": "",
        "certificate": "",
        "useselfsignedcertificate": false,
        "sslterminated": false,
        "verboselogging": false
    },
    {
        "id": "dc92d003f608a963",
        "type": "global-config",
        "env": [],
        "modules": {
            "node-red-contrib-telegrambot": "17.4.17"
        }
    }
]